ShorelineFromImage.cp312-win_amd64.pyd
test.py
ShorelineFromImage-1.3.2.dist-info/METADATA
ShorelineFromImage-1.3.2.dist-info/WHEEL
ShorelineFromImage-1.3.2.dist-info/top_level.txt
ShorelineFromImage-1.3.2.dist-info/RECORD
