Metadata-Version: 2.1
Name: ShorelineFromImage
Version: 1.3.2
Summary: Image-based shoreline extraction utilities and Python extension modules.
Author-email: Lei Wang <leiwang@lsu.edu>
License: MIT
Keywords: image-processing,shoreline,python-cpp,gis
